<?xml version="1.0" encoding="utf-8" ?>
<dwsync>
<file name="fwd.png" server="50.62.160.137/httpdocs/HAI/" local="130783465800000000" remote="130783465800000000" Dst="2" />
<file name="large1.jpg" server="50.62.160.137/httpdocs/HAI/" local="130783465800000000" remote="130783465800000000" Dst="2" />
<file name="large10.jpg" server="50.62.160.137/httpdocs/HAI/" local="130783465800000000" remote="130783465800000000" Dst="2" />
<file name="large11.jpg" server="50.62.160.137/httpdocs/HAI/" local="130783465800000000" remote="130783465800000000" Dst="2" />
<file name="large12.jpg" server="50.62.160.137/httpdocs/HAI/" local="130783465800000000" remote="130783465800000000" Dst="2" />
<file name="large13.jpg" server="50.62.160.137/httpdocs/HAI/" local="130783465800000000" remote="130783465800000000" Dst="2" />
<file name="large14.jpg" server="50.62.160.137/httpdocs/HAI/" local="130783465800000000" remote="130783465800000000" Dst="2" />
<file name="large15.jpg" server="50.62.160.137/httpdocs/HAI/" local="130783465800000000" remote="130783465800000000" Dst="2" />
<file name="large16.jpg" server="50.62.160.137/httpdocs/HAI/" local="130783465800000000" remote="130783465800000000" Dst="2" />
<file name="large17.jpg" server="50.62.160.137/httpdocs/HAI/" local="130783465800000000" remote="130783465800000000" Dst="2" />
<file name="large18.jpg" server="50.62.160.137/httpdocs/HAI/" local="130783465800000000" remote="130783465800000000" Dst="2" />
<file name="large2.jpg" server="50.62.160.137/httpdocs/HAI/" local="130783465800000000" remote="130783465800000000" Dst="2" />
<file name="large3.jpg" server="50.62.160.137/httpdocs/HAI/" local="130783465800000000" remote="130783465800000000" Dst="2" />
<file name="large4.jpg" server="50.62.160.137/httpdocs/HAI/" local="130783465800000000" remote="130783465800000000" Dst="2" />
<file name="large5.jpg" server="50.62.160.137/httpdocs/HAI/" local="130783465800000000" remote="130783465800000000" Dst="2" />
<file name="large6.jpg" server="50.62.160.137/httpdocs/HAI/" local="130783466400000000" remote="130783466400000000" Dst="2" />
<file name="large7.jpg" server="50.62.160.137/httpdocs/HAI/" local="130783466400000000" remote="130783466400000000" Dst="2" />
<file name="large8.jpg" server="50.62.160.137/httpdocs/HAI/" local="130783466400000000" remote="130783466400000000" Dst="2" />
<file name="large9.jpg" server="50.62.160.137/httpdocs/HAI/" local="130783466400000000" remote="130783466400000000" Dst="2" />
<file name="small-360.jpg" server="50.62.160.137/httpdocs/HAI/" local="130783466400000000" remote="130783466400000000" Dst="2" />
<file name="small-alex.jpg" server="50.62.160.137/httpdocs/HAI/" local="130783466400000000" remote="130783466400000000" Dst="2" />
<file name="small-corina.jpg" server="50.62.160.137/httpdocs/HAI/" local="130783466400000000" remote="130783466400000000" Dst="2" />
<file name="small-evp.jpg" server="50.62.160.137/httpdocs/HAI/" local="130783466400000000" remote="130783466400000000" Dst="2" />
<file name="small-fwd.jpg" server="50.62.160.137/httpdocs/HAI/" local="130783466400000000" remote="130783466400000000" Dst="2" />
<file name="small-grid.jpg" server="50.62.160.137/httpdocs/HAI/" local="130783466400000000" remote="130783466400000000" Dst="2" />
<file name="small-inna.jpg" server="50.62.160.137/httpdocs/HAI/" local="130783466400000000" remote="130783466400000000" Dst="2" />
<file name="small-lora.jpg" server="50.62.160.137/httpdocs/HAI/" local="130783466400000000" remote="130783466400000000" Dst="2" />
<file name="small-mafia.jpg" server="50.62.160.137/httpdocs/HAI/" local="130783466400000000" remote="130783466400000000" Dst="2" />
<file name="small-mlp.jpg" server="50.62.160.137/httpdocs/HAI/" local="130783466400000000" remote="130783466400000000" Dst="2" />
<file name="small-msp.jpg" server="50.62.160.137/httpdocs/HAI/" local="130783466400000000" remote="130783466400000000" Dst="2" />
<file name="small-r3dcar.jpg" server="50.62.160.137/httpdocs/HAI/" local="130783466400000000" remote="130783466400000000" Dst="2" />
<file name="small-r3dcov.jpg" server="50.62.160.137/httpdocs/HAI/" local="130783466400000000" remote="130783466400000000" Dst="2" />
<file name="small-rap.jpg" server="50.62.160.137/httpdocs/HAI/" local="130783466400000000" remote="130783466400000000" Dst="2" />
<file name="small-rdm.jpg" server="50.62.160.137/httpdocs/HAI/" local="130783466400000000" remote="130783466400000000" Dst="2" />
<file name="small-ruby.jpg" server="50.62.160.137/httpdocs/HAI/" local="130783466400000000" remote="130783466400000000" Dst="2" />
<file name="small-s3dcov.jpg" server="50.62.160.137/httpdocs/HAI/" local="130783466400000000" remote="130783466400000000" Dst="2" />
<file name="small-sava.jpg" server="50.62.160.137/httpdocs/HAI/" local="130783466400000000" remote="130783466400000000" Dst="2" />
<file name="small-stan.jpg" server="50.62.160.137/httpdocs/HAI/" local="130783466400000000" remote="130783466400000000" Dst="2" />
<file name="small-u3dcar.jpg" server="50.62.160.137/httpdocs/HAI/" local="130783466400000000" remote="130783466400000000" Dst="2" />
<file name="small-zoomer.jpg" server="50.62.160.137/httpdocs/HAI/" local="130783466400000000" remote="130783466400000000" Dst="2" />
</dwsync>